olimp/__init__.py
olimp/processing.py
olimp/dataset/__init__.py
olimp/dataset/_zenodo.py
olimp/dataset/cvd.py
olimp/dataset/olimp.py
olimp/dataset/sca_2023.py
olimp/demo_data/73.png
olimp/demo_data/__init__.py
olimp/demo_data/horse.jpg
olimp/evaluation/__init__.py
olimp/evaluation/cs/__init__.py
olimp/evaluation/cs/cielab.py
olimp/evaluation/cs/hls.py
olimp/evaluation/cs/hsv.py
olimp/evaluation/cs/linrgb.py
olimp/evaluation/cs/lms.py
olimp/evaluation/cs/oklab.py
olimp/evaluation/cs/opponent.py
olimp/evaluation/cs/prolab.py
olimp/evaluation/cs/srgb.py
olimp/evaluation/loss/__init__.py
olimp/evaluation/loss/_base.py
olimp/evaluation/loss/chromaticity_difference.py
olimp/evaluation/loss/contrast_similarity.py
olimp/evaluation/loss/corr.py
olimp/evaluation/loss/cvd_swin_loss.py
olimp/evaluation/loss/flip.py
olimp/evaluation/loss/lcn.py
olimp/evaluation/loss/lpips.py
olimp/evaluation/loss/mse.py
olimp/evaluation/loss/nrmse.py
olimp/evaluation/loss/piq.py
olimp/evaluation/loss/psnr.py
olimp/evaluation/loss/rms.py
olimp/evaluation/loss/rmse.py
olimp/evaluation/loss/s_oklab.py
olimp/evaluation/loss/ssim.py
olimp/evaluation/loss/stress.py
olimp/evaluation/loss/vae.py
olimp/evaluation/train/__init__.py
olimp/evaluation/train/dataset.py
olimp/evaluation/train/grid_search_optimize_params.py
olimp/evaluation/train/human_metric_alignment.py
olimp/evaluation/train/human_studies_download.py
olimp/evaluation/train/loss.py
olimp/evaluation/train/train.py
olimp/evaluation/train/models/__init__.py
olimp/evaluation/train/models/basic_block.py
olimp/evaluation/train/models/learned_formula.py
olimp/examples/README.md
olimp/examples/__init__.py
olimp/examples/pyolimp_train.py
olimp/examples/precompensation/achromatic_daltonization.py
olimp/examples/precompensation/bregman_jumbo.py
olimp/examples/precompensation/cvd_direct_optimization.py
olimp/examples/precompensation/feng_xu.py
olimp/examples/precompensation/global_tone_mapping.py
olimp/examples/precompensation/hqs.py
olimp-1.0.6.dist-info/licenses/LICENSE
olimp-1.0.6.dist-info/METADATA
olimp-1.0.6.dist-info/WHEEL
olimp-1.0.6.dist-info/top_level.txt
olimp-1.0.6.dist-info/RECORD
