Metadata-Version: 2.4
Name: olimp
Version: 1.0.6
Summary: Framework for Image Precompensation
Author-email: Nafe Alkzir <nafe93@windowslive.com>, Arseniy Terekhin <senyai@gmail.com>, Sergey Gladilin <gladilin@gmail.com>, Dmitry Nikolaev <d.p.nikolaev@gmail.com>, Ivan Konovalenko <konovalenko@iitp.ru>
License: MIT
Project-URL: Homepage, https://github.com/pyolimp/pyolimp
Project-URL: Bug Reports, https://github.com/pyolimp/pyolimp/issues
Classifier: Programming Language :: Python :: 3
Classifier: License :: OSI Approved :: MIT License
Classifier: Operating System :: OS Independent
Classifier: Typing :: Typed
Requires-Python: >=3.10
License-File: LICENSE
Requires-Dist: setuptools==69.0.3
Requires-Dist: requests==2.28.2
Requires-Dist: pillow>=11.2.1
Requires-Dist: numpy<2
Requires-Dist: torch<3,>=2.4.0
Requires-Dist: matplotlib==3.9.2
Requires-Dist: rich==13.8.0
Requires-Dist: torchvision>=0.19.0
Requires-Dist: piq==0.8.0
Requires-Dist: json5==0.12.1
Requires-Dist: pydantic>=2.6.4
Requires-Dist: segmentation_models_pytorch==0.3.4
Requires-Dist: ballfish==0.4.0
Requires-Dist: lpips==0.1.4
Dynamic: license-file
